dg_face_tracking/DataFaceApp.py
dg_face_tracking/__init__.py
dg_face_tracking/_version.py
dg_face_tracking/config_rt.py
dg_face_tracking/embeds_compare.py
dg_face_tracking/embeds_estimate.py
dg_face_tracking/estimate_accuracy.py
dg_face_tracking/face_tracker_controller.py
dg_face_tracking/manage_db.py
dg_face_tracking/track_faces.py
dg_face_tracking/Consumers/__init__.py
dg_face_tracking/Consumers/consumer.py
dg_face_tracking/Consumers/consumer_factory.py
dg_face_tracking/Consumers/embeds_writer.py
dg_face_tracking/Consumers/lancedb_writer.py
dg_face_tracking/Consumers/localdb_writer.py
dg_face_tracking/Consumers/pairwise_stats.py
dg_face_tracking/Data/basedata.py
dg_face_tracking/Data/face_data.py
dg_face_tracking/Data/frame_data.py
dg_face_tracking/DataSource/CameraSource.py
dg_face_tracking/DataSource/DatasetSource.py
dg_face_tracking/DataSource/FolderSource.py
dg_face_tracking/DataSource/__init__.py
dg_face_tracking/DataSource/datasource.py
dg_face_tracking/DataSource/datasource_factory.py
dg_face_tracking/DataSource/face_tracker.py
dg_face_tracking/DataSource/face_tracker_demo.py
dg_face_tracking/Database/DBAdapter.py
dg_face_tracking/Database/LocalDBAdapter.py
dg_face_tracking/Database/__init__.py
dg_face_tracking/Database/vectstore.py
dg_face_tracking/Face2ID/__init__.py
dg_face_tracking/Face2ID/face2id.py
dg_face_tracking/Face2ID/face2id_proc.py
dg_face_tracking/Frontend/DataFaceDoc.py
dg_face_tracking/Frontend/DataFaceFrontend.py
dg_face_tracking/Frontend/DataFaceView.py
dg_face_tracking/Frontend/__init__.py
dg_face_tracking/Frontend/frontend_factory.py
dg_face_tracking/Frontend/main_window.py
dg_face_tracking/Process/dg_process.py
dg_face_tracking/Processors/__init__.py
dg_face_tracking/Processors/deepface_embedder.py
dg_face_tracking/Processors/face_detector.py
dg_face_tracking/Processors/face_embedder.py
dg_face_tracking/Processors/lancedb_searcher.py
dg_face_tracking/Processors/processor.py
dg_face_tracking/Processors/processor_factory.py
dg_face_tracking-0.1.15.dist-info/METADATA
dg_face_tracking-0.1.15.dist-info/WHEEL
dg_face_tracking-0.1.15.dist-info/entry_points.txt
dg_face_tracking-0.1.15.dist-info/top_level.txt
dg_face_tracking-0.1.15.dist-info/RECORD
