Metadata-Version: 2.1
Name: dg_face_tracking
Version: 0.1.15
Summary: DeGirum Face Tracking Application Package
Home-page: https://github.com/degirum
Author: DeGirum Corp.
Author-email: support@degirum.com
Classifier: Topic :: Scientific/Engineering :: Artificial Intelligence
Classifier: Development Status :: 3 - Alpha
Classifier: Programming Language :: Python :: 3
Classifier: License :: Other/Proprietary License
Requires-Python: >=3.9
Requires-Dist: config
Requires-Dist: ffmpeg
Requires-Dist: pandas
Requires-Dist: opencv-python
Requires-Dist: degirum
Requires-Dist: degirum-tools
Requires-Dist: names-generator
Requires-Dist: filterpy
Requires-Dist: scikit-learn
Requires-Dist: rich
Requires-Dist: lancedb
Requires-Dist: validators
